easier/__init__.py
easier/agent_runner.py
easier/bernstein.py
easier/bigquery.py
easier/cli.py
easier/clock.py
easier/create_makefile.py
easier/crypt.py
easier/dataframe_tools.py
easier/distributions.py
easier/duck_frame.py
easier/duck_mirror.py
easier/duckcacher.py
easier/ecdf_lib.py
easier/ez_agent.py
easier/fit_lib.py
easier/gemini.py
easier/gsheet.py
easier/hvtools.py
easier/item.py
easier/item_new.py
easier/iterify.py
easier/lomb_scargle.py
easier/memory.py
easier/metabase.py
easier/minimodel_orig.py
easier/normal_sampler.py
easier/outlier_tools.py
easier/param_state.py
easier/plotting.py
easier/postgres.py
easier/print_catcher.py
easier/proportion_lib.py
easier/shaper.py
easier/stream_plotter.py
easier/timer.py
easier/tracker.py
easier/utils.py
easier/vonmises.py
easier/experimental/duckmirror.py
easier/experimental/duckmirrorspec.py
easier/experimental/test_duckmirror.py
easier/filtering/__init__.py
easier/filtering/elliptic_filter.py
easier/filtering/tvd.py
easier/marimo_pipeline_template/pipeline.py
easier/marimo_pipeline_template/manifest/marimo_pipeline_template.zip
easier/marimo_pipeline_template/pipeline_template_files/template_process_with_llm.nb.py
easier/marimo_pipeline_template/pipeline_template_files/template_replica_query.nb.py
easier/tests/__init__.py
easier/tests/test_agent_runner.py
easier/tests/test_bernstein.py
easier/tests/test_crypt.py
easier/tests/test_dataframe_tools.py
easier/tests/test_duck_frame.py
easier/tests/test_duckcacher.py
easier/tests/test_ecdf_lib.py
easier/tests/test_ez_agent.py
easier/tests/test_ez_agent_integration.py
easier/tests/test_iterify.py
easier/tests/test_utils_blob_attr.py
easier/tests/test_utils_other.py
easier/tests/test_utils_pickle_cache.py
easier-1.9.11.dist-info/licenses/LICENSE
easier-1.9.11.dist-info/METADATA
easier-1.9.11.dist-info/WHEEL
easier-1.9.11.dist-info/entry_points.txt
easier-1.9.11.dist-info/top_level.txt
easier-1.9.11.dist-info/RECORD
