Metadata-Version: 2.4
Name: easier
Version: 1.9.11
Summary: Tools for analysis
Author-email: Rob deCarvalho <unlisted@unlisted.net>
License: MIT
Project-URL: Homepage, https://github.com/robdmc/easier
Project-URL: Repository, https://github.com/robdmc/easier
Classifier: Programming Language :: Python :: 3.11
Classifier: Intended Audience :: Developers
Classifier: License :: OSI Approved :: MIT License
Classifier: Operating System :: OS Independent
Requires-Python: >=3.11
License-File: LICENSE
Requires-Dist: astropy
Requires-Dist: asgiref
Requires-Dist: click
Requires-Dist: cog
Requires-Dist: cryptography
Requires-Dist: cvxpy
Requires-Dist: daiquiri
Requires-Dist: dataset
Requires-Dist: django
Requires-Dist: duckdb
Requires-Dist: fuzzypicker
Requires-Dist: gatspy
Requires-Dist: google-api-python-client
Requires-Dist: google-auth
Requires-Dist: google-generativeai
Requires-Dist: gspread
Requires-Dist: holoviews
Requires-Dist: ibis-framework
Requires-Dist: importlib-metadata
Requires-Dist: IPython
Requires-Dist: jinja2
Requires-Dist: matplotlib
Requires-Dist: numpy
Requires-Dist: pandas
Requires-Dist: pandas-gbq
Requires-Dist: pandera
Requires-Dist: polars
Requires-Dist: psutil
Requires-Dist: pydantic-ai
Requires-Dist: python-dateutil
Requires-Dist: requests
Requires-Dist: scikit-learn
Requires-Dist: scipy
Requires-Dist: simple-salesforce
Requires-Dist: tqdm
Provides-Extra: dev
Requires-Dist: coverage; extra == "dev"
Requires-Dist: flake8; extra == "dev"
Requires-Dist: pytest; extra == "dev"
Requires-Dist: pytest-asyncio; extra == "dev"
Requires-Dist: pytest-cov; extra == "dev"
Requires-Dist: pytest-xdist; extra == "dev"
Requires-Dist: pyright; extra == "dev"
Dynamic: license-file
